enedis_tic/__init__.py
enedis_tic/application_layer.py
enedis_tic/autodetect.py
enedis_tic/euridis.json
enedis_tic/infos.json
enedis_tic/link_layer.py
enedis_tic/physical_layer.py
enedis_tic-0.2.0.dist-info/METADATA
enedis_tic-0.2.0.dist-info/WHEEL
enedis_tic-0.2.0.dist-info/licenses/LICENSE
enedis_tic-0.2.0.dist-info/RECORD
